angular_curd_gen/admin.py
angular_curd_gen/config.py
angular_curd_gen/field.py
angular_curd_gen/register.py
angular_curd_gen/templates/api.jinja
angular_curd_gen/templates/api.spec.jinja
angular_curd_gen/templates/interfaces.jinja
angular_curd_gen/templates/module.jinja
angular_curd_gen/templates/routers.jinja
angular_curd_gen/templates/creator_component/css.jinja
angular_curd_gen/templates/creator_component/html.jinja
angular_curd_gen/templates/creator_component/spec.ts.jinja
angular_curd_gen/templates/creator_component/ts.jinja
angular_curd_gen/templates/dashboard_component/css.jinja
angular_curd_gen/templates/dashboard_component/html.jinja
angular_curd_gen/templates/dashboard_component/spec.ts.jinja
angular_curd_gen/templates/dashboard_component/ts.jinja
angular_curd_gen/templates/list_component/css.jinja
angular_curd_gen/templates/list_component/html.jinja
angular_curd_gen/templates/list_component/spec.ts.jinja
angular_curd_gen/templates/list_component/ts.jinja
angular_curd_gen/templates/macros/com_field.jinja
angular_curd_gen/templates/macros/form_field.jinja
angular_curd_gen/templates/macros/list_filter_params.jinja
angular_curd_gen/templates/macros/rust_module.jinja
angular_curd_gen/templates/macros/ts.spec.jinja
angular_curd_gen/templates/rust/.gitignore.jinja
angular_curd_gen/templates/rust/Cargo.toml.jinja
angular_curd_gen/templates/rust/src/config.rs.jinja
angular_curd_gen/templates/rust/src/lib.rs.jinja
angular_curd_gen/templates/rust/src/main.rs.jinja
angular_curd_gen/templates/rust/src/entities/mod.rs.jinja
angular_curd_gen/templates/rust/src/entities/models/auth.rs.jinja
angular_curd_gen/templates/rust/src/entities/models/demo.rs.jinja
angular_curd_gen/templates/rust/src/entities/models/log.rs.jinja
angular_curd_gen/templates/rust/src/entities/models/mod.rs.jinja
angular_curd_gen/templates/rust/src/entities/models/model.rs.jinja
angular_curd_gen/templates/rust/src/entities/tables/mod.rs.jinja
AngularCurdGen-0.3.0.dist-info/METADATA
AngularCurdGen-0.3.0.dist-info/WHEEL
AngularCurdGen-0.3.0.dist-info/top_level.txt
AngularCurdGen-0.3.0.dist-info/RECORD
