Metadata-Version: 2.1
Name: AngularCurdGen
Version: 0.3.0
Summary: Use for generate angular curd codes.
Home-page: https://github.com/StevenLianaL/angular_curd_gen
Author: Steven Wang
Author-email: brightstar8284@icloud.com
Classifier: Programming Language :: Python :: 3.10
Classifier: License :: OSI Approved :: MIT License
